{
    "DP001": {"estado": "No entregado"},
    "DP002": {"estado": "No entregado"},
    "DP003": {"estado": "No entregado"},
    "DP004": {"estado": "No entregado"},
    "DP005": {"estado": "No entregado"},
    "DP006": {"estado": "No entregado"},
    "DP007": {"estado": "No entregado"},
    "DP008": {"estado": "No entregado"},
    "DP009": {"estado": "No entregado"},
    "DP010": {"estado": "No entregado"},
    "DP011": {"estado": "No entregado"},
    "DP012": {"estado": "No entregado"},
    "DP013": {"estado": "No entregado"},
    "DP014": {"estado": "No entregado"},
    "DP015": {"estado": "No entregado"},
    "DP016": {"estado": "No entregado"},
    "DP017": {"estado": "No entregado"},
    "DP018": {"estado": "No entregado"},
    "DP019": {"estado": "No entregado"},
    "DP020": {"estado": "No entregado"},
    "DP021": {"estado": "No entregado"},
    "DP022": {"estado": "No entregado"},
    "DP023": {"estado": "Entregado"},
    "DP024": {"estado": "No entregado"},
    "DP025": {"estado": "Entregado"},
    "DP026": {"estado": "Entregado"},
    "DP027": {"estado": "No entregado"},
    "DP028": {"estado": "Entregado"},
    "DP029": {"estado": "Entregado"},
    "DP030": {"estado": "Entregado"},
    "DP031": {"estado": "Entregado"},
    "DP032": {"estado": "Entregado"}
}
